setup.py
client/__init__.py
client/client.py
client/common/__init__.py
client/common/decos.py
client/common/descryptors.py
client/common/errors.py
client/common/metaclasses.py
client/common/utils.py
client/common/variables.py
client/logs/__init__.py
client/logs/config_client_log.py
client/logs/config_server_log.py
client/unit_tests/__init__.py
client/unit_tests/test_client.py
client/unit_tests/test_utils.py
mess_client_rakitin.egg-info/PKG-INFO
mess_client_rakitin.egg-info/SOURCES.txt
mess_client_rakitin.egg-info/dependency_links.txt
mess_client_rakitin.egg-info/requires.txt
mess_client_rakitin.egg-info/top_level.txt