Metadata-Version: 1.0
Name: mess-client-rakitin
Version: 0.0.1
Summary: message_server
Home-page: UNKNOWN
Author: Alexey Rakitin
Author-email: amrakitin@gmail.com
License: UNKNOWN
Platform: UNKNOWN
